multiregex/__init__.py
multiregex/py.typed
multiregex-2.0.3.dist-info/LICENSE
multiregex-2.0.3.dist-info/METADATA
multiregex-2.0.3.dist-info/WHEEL
multiregex-2.0.3.dist-info/top_level.txt
multiregex-2.0.3.dist-info/RECORD
