Metadata-Version: 2.1
Name: multiregex
Version: 2.0.3
Summary: Quickly match many regexes against a string. Provides 2-10x speedups over naïve regex matching.
Author-email: "QuantCo, Inc." <noreply@quantco.com>, Jonas Haag <jonas@lophus.org>
Maintainer-email: Bela Stoyan <bela.stoyan@quantco.com>
Project-URL: Home, https://github.com/quantco/multiregex
Classifier: Programming Language :: Python :: 3
Classifier: Programming Language :: Python :: 3.8
Classifier: Programming Language :: Python :: 3.9
Classifier: Programming Language :: Python :: 3.10
Classifier: Programming Language :: Python :: 3.11
Classifier: Programming Language :: Python :: 3.12
Requires-Python: >=3.8
License-File: LICENSE
Requires-Dist: pyahocorasick
